dandelion/LICENSE
dandelion/__init__.py
dandelion/activation.py
dandelion/ctc_theano.py
dandelion/functional.py
dandelion/initialization.py
dandelion/module.py
dandelion/objective.py
dandelion/update.py
dandelion/util.py
dandelion/ext/__init__.py
dandelion/ext/CV/CV.py
dandelion/ext/CV/__init__.py
dandelion/ext/visual/__init__.py
dandelion/ext/visual/visual.py
dandelion/model/AlternateLSTM2D.py
dandelion/model/__init__.py
dandelion/model/ctpn.py
dandelion/model/feature_pyramid_net.py
dandelion/model/resnet.py
dandelion/model/shufflenet.py
dandelion/model/unet.py
dandelion/model/vgg.py
Dandelion-0.17.26.dist-info/LICENSE
Dandelion-0.17.26.dist-info/METADATA
Dandelion-0.17.26.dist-info/WHEEL
Dandelion-0.17.26.dist-info/top_level.txt
Dandelion-0.17.26.dist-info/RECORD
