Metadata-Version: 2.1
Name: Dandelion
Version: 0.17.26
Summary: A light weight deep learning framework
Home-page: https://github.com/david-leon/Dandelion
Author: David Leon (Dawei Leng)
Author-email: daweileng@outlook.com
License: Mozilla Public License v2.0
Keywords: DL framework,Theano
Platform: UNKNOWN
Classifier: Intended Audience :: Developers
Classifier: Intended Audience :: Science/Research
Classifier: License :: OSI Approved :: Mozilla Public License 2.0 (MPL 2.0)
Classifier: Programming Language :: Python :: 3
Classifier: Programming Language :: Python :: 3.5
Classifier: Programming Language :: Python :: 3.6
Classifier: Topic :: Scientific/Engineering :: Artificial Intelligence
